{
  "بسم": "In the name",
  "الله": "Allah",
  "الرحمن": "The Most Gracious",
  "الرحيم": "The Most Merciful",
  "وبعد:": "And after that:",
  "وحارت": "And he became perplexed",
  "فيها": "In it",
  "الألباب!": "O you of understanding!",
  "ومحاسبة": "And accounting",
  "هذا": "This",
  "اللقاء": "The meeting",
  "تقف": "She stops.",
  "بك": "Bik.",
  "عند": "At",
  "واحد": "One",
  "من": "From",
  "تلك": "Those",
  "الأسرار": "The Secrets",
  "البديعة": "The Badi'ah",
  "وتارة": "At times,",
  "يدعوه": "He calls upon him",
  "إلى": "to",
  "الشر!": "Evil!",
  "النَّفس!": "The soul!",
  "العجيبة": "The wonderful",
  "الفريدة!": "al-Fariḍah!",
  "ومستودع": "And the warehouse",
  "الأسرار!": "The Secrets!",
  "عدو": "Enemy",
  "في": "In",
  "ثياب": "Clothing",
  "صديق!": "Friend!",
  "(هل": "(Is",
  "جاهدت": "I fought",
  "نفسك؟": "Your self?",
  "ومضة": "A flash",
  "ومضات:": "Flashes:",
  "(سلسلة": "(Chain",
  "المحاسبة)": "Accounting",
  "وطليعة": "And a vanguard",
  "درب": "Darbon",
  "محاسبة": "accounting",
  "النَّفس": "The self",
  "أخي": "My brother",
  "المسلم:": "The Muslim:",
  "أتدري": "Do you know?",
  "ما": "What",
  "هو": "He",
  "جهاد": "Jihad",
  "النفس؟": "The soul?",
  "إنَّه:": "Indeed, he is",
  "جهادٌ": "Jihad",
  "ويحك": "O woe to you",
  "إن": "Indeed",
  "هُزمت": "هُزمت",
  "فيه!": "In it! [Surah al-Duha (93): Ayah 7]",
  "وبأس": "And with severity",
  "شديد!": "Severe!",
  "جهادُ": "Jihad",
  "كامن": "hidden",
  "بين": "Between",
  "جنبيك!": "I keep myself apart from you!",
  "إنَّه": "Indeed, he",
  "أشد": "more severe",
  "أهل": "People",
  "الكفر": "disbelief",
  "والإلحاد!": "and atheism!",
  "وأما": "As for",
  "معنى": "Meaning",
  "النفس:": "The soul",
  "فإن": "If then,",
  "وهي": "And she is",
  "تجاهده": "He struggled against him",
  "بما": "With what",
  "تركن": "Tarkun",
  "إليه»": "To him,",
  "وتجنبها": "And avoid it",
  "طرق": "Ways",
  "المعاصي": "Sins",
  "والشهوات": "And desires",
  "و": "And",
  "النفوس": "The souls",
  "ثلاثة": "Three",
  "وتحض": "and trains",
  "على": "Upon",
  "الأخلاق": "Ethics",
  "الذميمة": "al-Zamīmah",
  "فتلوم": "But you blame",
  "نفسها": "herself",
  "واتصفت": "And he attributed",
  "بالصفات": "By the attributes",
  "الجميلة": "The Beautiful",
  "أين": "Where",
  "أنت": "You",
  "جهادك": "Your Jihad",
  "فرض": "Obligation",
  "عين": "Eye",
  "كل": "All",
  "أحد؟": "One?",
  "ولكن": "But",
  "النفس": "The soul",
  "عين؟": "Eye?",
  "ثم": "Then",
  "اسع": "Asʿa",
  "جاهدًا": "striving",
  "مجاهدتها": "Her Jihad",
  "ومخالفة": "Opposition",
  "هواها": "The air of it",
  "فكان": "Then it became",
  "له": "To him",
  "قائدًا)": "Leader",
  "وحتى": "And even",
  "يعلم": "He knows",
  "ملبسه": "Her clothing",
  "ومطعمه": "and his provision",
  "ومشربه)": "And his drink",
  "هل": "Is",
  "علمت": "I have learned",
  "أن": "Indeed, if a person were to perform an obligatory act within it, it would be as if he had performed seventy obligatory acts at other times.",
  "نفسك": "your self",
  "التي": "The",
  "جنبيك": "I will keep you informed",
  "أول": "First",
  "أعدائك؟": "Are they your enemies?",
  "جاء": "He came",
  "وصية": "Wasiyyah",
  "أبي": "My father",
  "بكر": "Bukar",
  "الصديق": "The Friend",
  "عمر": "Omar",
  "بن": "bin",
  "الخطاب": "The address",
  "رضي": "May Allāh be pleased with him/her/them.",
  "عنهما": "On them",
  "لما": "When",
  "استخلفه:": "he appointed him as a successor",
  "«إن": "Surely",
  "أحذِّرك": "I warn you",
  "ومن": "And among",
  "بترك": "By leaving",
  "الشهوات)": "The desires",
  "فبادروا": "Hasten",
  "قبل": "Before",
  "جهاد!": "Jihad!",
  "واحترسوا": "And be cautious",
  "شرورها": "its evils",
  "فما": "So what",
  "أحوج": "Ahuw",
  "هذه": "This",
  "يردُّ": "He responds",
  "عدوانها": "Her aggression",
  "قال": "He said,",
  "الحسن": "The Good",
  "البصري:": "al-Basri",
  "«ما": "What",
  "الدابة": "The animal",
  "الجموح": "The rush",
  "بأحوج": "Baha'j",
  "اللجام": "The bridle",
  "الشديد": "The Almighty",
  "نفسك!": "Your soul!",
  "حتى": "Until",
  "يخضر": "It greens",
  "جسده": "His body",
  "ويصفر!": "And it turns yellow!",
  "علقمة": "Al-ʿIqma",
  "قيس": "Qays",
  "يقول": "He says,",
  "له:": "For him:",
  "لم": "No",
  "تعذب": "suffer",
  "فيقول:": "He says:",
  "كرامتها": "Her dignity",
  "أريد!": "I want!",
  "وعفوا": "And pardon",
  "عنك!": "",
  "يا": "O",
  "أماه": "O Mother",
  "هي": "It is",
  "نفسي!": "My soul!",
  "ترميه": "He throws it away.",
  "المهالك!": "The Ruin!",
  "وهل": "And indeed",
  "أهلك": "Owing to",
  "الهوى": "al-hawā",
  "إلاَّ": "Except",
  "تهاونهم": "Their leniency",
  "بشرور": "Bashshur",
  "أنفسهم؟": "themselves?",
  "أقلَّ": "Aqal",
  "فلاحك": "Your success",
  "ابن": "Ibn",
  "آدم": "Adam",
  "إذا": "If",
  "أطلقت": "She launched",
  "زمامك": "Zamamka",
  "لنفسك": "For yourself",
  "تقودك": "It leads you",
  "حيث": "Where",
  "شاءت!": "She desired!",
  "أيها": "O",
  "العاقل!": "The wise one!",
  "أي": "Indeed",
  "سلاح": "weapon",
  "هيأته": "His provision",
  "لجهاد": "For Jihad",
  "لتخرج": "Let her leave",
  "منتصرًا": "victorious",
  "معركة": "Mعركة",
  "حامية!": " حامية! ",
  "حقًا": "Indeed",
  "إنها": "Indeed, it is.",
  "فإنك": "Indeed, you",
  "تواجه": "You face",
  "عدوًا": "enemy",
  "كامنًا": "latent",
  "فعلتم": "You have done",
  "الجهاد": "Jihad",
  "الأكبر؟": "The greatest?",
  "قالوا:": "They said:",
  "وما": "And what",
  "قال:": "He said:",
  "القلب!": "The heart!",
  "جهادهما": "Their jihad",
  "أعظم": "The greatest",
  "الجهاد)": "Jihad",
  "ولن": "And never",
  "تجد": "You will find",
  "الأعمال": "The Works",
  "أشق": "Ashiq",
  "جهادها!": "Her Jihad!",
  "وأهله": "And his family",
  "هم": "They",
  "أعلى": "Aʿlā",
  "الناس": "The people",
  "مقامًا": "a station",
  "وابدأ": "And begin",
  "بنفسك": "With yourself",
  "فاغزها)": "Go out to her.",
  "انتصارك": "Your victory",
  "فهنيئًا": "Congratulations!",
  "لك": "For you",
  "يوم": "Day",
  "تركز": "He concentrated",
  "راية": "Rai'a",
  "النصر": "The Victory",
  "خَفَّاقة": "خَفَّاقة",
  "أرض": "Land",
  "سيطرت": "Gained control of",
  "عليها": "Upon it",
  "شهوات": "Desires",
  "وأهواؤها!": "And her desires!",
  "وغلب": "and overwhelmed",
  "هواه": "His desire",
  "والغضب": "And anger",
  "والطمع»": "And greed,",
  "وقيل": "It is said,",
  "ليحيى": "To live",
  "معاذ:": "",
  "(من": "(from",
  "اصح": "he is healthy",
  "عزمًا؟": "With determination?",
  "(لغالب": "",
  "لهواه)": "for his amusement,",
  "وُفِّقتَ": "You have been granted success",
  "ذلك": "That",
  "فأنت": "So you",
  "يومها": "That day",
  "المجاهد": "The Fighter",
  "حقًا!": "Truly!",
  "والمهاجر": "And the Emigrant",
  "هَجَرَ": "Hajr",
  "الخطايا": "The sins",
  "والذنوب)": "and sins",
  "[رواه": "[He transmitted it",
  "أحمد": "Ahmed",
  "وغيره/": "and others",
  "السلسلة": "The Chain",
  "الصحيحة:": "The correct one",
  "وأعدَّ": "And prepare",
  "كتائبه": "His battalions",
  "النفس!": "The soul!",
  "بل": "Rather",
  "أصل": "Origin",
  "كان": "He was",
  "مقدَّمًا": " Presented in advance,",
  "العدو": "The enemy",
  "الخارج": "The one who goes out",
  "وجاهدها": "And strive against it",
  "مَنْ": "Who",
  "يجاهدُ": "He strives",
  "غازيًا": "Ghazi",
  "أعداءَ": "Enemies",
  "دين": "Religion",
  "يرجُو": "He hopes",
  "أنْ": "that",
  "يُعَانَ": "Yū‘ān",
  "ويُنْصرَا": "And they will be supported",
  "هلاَّ": "Hala",
  "غَشِيتَ": "ghashita",
  "النِّفْسَ": "The soul",
  "غَزوًا": "غَزوًا",
  "إنَّها": "Indeed, it is...",
  "أعْدَى": "A'uda",
  "عدوِّك": "your enemy",
  "كي": "how",
  "تفوزَ": "You will overcome/victorious",
  "وتَظفرَا": "and gain victory",
  "مهما": "no matter how",
  "عَنَيْتَ": "You have taken care of",
  "جهادَها": "Her Jihad",
  "وعنادَها": "and her obstinacy",
  "فلقد": "For indeed",
  "تعاطَيْتَ": "You dealt with or engaged in",
  "الجهادَ": "The Jihad",
  "الأكبرَا": "al-Akbara",
  "الزم": "He adhered",
  "تفُزْ": "tufuz",
  "بتلك": "With those",
  "الجنان": "The gardens",
  "لتتوافر": "Let it be made available",
  "لها": "To her",
  "الآخرة)": "The Hereafter",
  "وتحرِّكها": "And set them in motion",
  "بسوط": "With a whip",
  "المحاسبة": "The reckoning",
  "ولمن": "And for those who",
  "رزُق": "Was granted",
  "الشَّرف": "The honor",
  "أتت": "She came",
  "بشارة": "With glad tidings",
  "النبي": "The Prophet",
  "صلى": "Pray",
  "عليه": "Upon him",
  "وسلم": "And do not exceed that,",
  "كهجرة": "Kahjrah",
  "إليَّ!": "To me!",
  "مسلم]": "Muslim",
  "ولا": "And",
  "يتفرع": "It branches off",
  "أفراد)": "Individuals",
  "وحاسبها": "And hold her accountable.",
  "الغريم": "The creditor",
  "لغريمه": "for her enemy",
  "ودار": "and abode",
  "فلان؟": "So-and-so?",
  "وكان": "And he was",
  "لنفسه:": "To himself:",
  "ومالك": "And Mālik",
  "الطعام": "The food",
  "نفس": "self",
  "الخبز": "bread",
  "والزيت!": "And the oil! \n",
  "الثياب": "Clothing",
  "إلا": "Except",
  "هذان": "These two",
  "الثوبان!": "The two garments!",
  "النساء": "The Women",
  "العجوز!": "The old woman!",
  "أفتحبين": "Aftahibeen",
  "تموتي؟": "Die?",
  "فقالت:": "She said:",
  "أنا": "I",
  "أصبر": "Be patient",
  "العيش!": "The life!",
  "الذين": "Those who",
  "جاهدوا": "They strove",
  "أنفسهم": "themselves",
  "جهادًا": " Jihad ",
  "لا": "No.",
  "يعرف": "He knows",
  "الهدنة!": "The Truce!",
  "ويا": "O",
  "لبشراه": "Labishrah",
  "بهذا": "With this",
  "العظيم!": "The Great One!",
  "ومثابرة": "And perseverance",
  "الطاعات": "The acts of obedience",
  "عن": "On the authority of",
  "المغيرة": "Al-Mughīrah",
  "شعبة": "Subhah",
  "عنه": "From him",
  "صلَّى": "he performed prayer",
  "انتفخت": "The boil bursted.",
  "قدماه!": "Both of his hands!",
  "فقيل": "And it was said,",
  "أتَكَلَّفُ": "Do I take upon myself?",
  "وقد": "And indeed",
  "غفر": "Ghafara",
  "تقدَّم": "Qaddam",
  "ذنبك": "your sin",
  "تأخر؟": "Delayed?",
  "فقال:": "He said:",
  "«أفلا": "Will you not",
  "أكون": "I would be",
  "عبدًا": "عبدًا",
  "شكورًا؟": "Thanks?",
  "البخاري": "Al-Bukhari",
  "ومسلم]": "And a Muslim",
  "بعدهم": "After them",
  "أولئك": "Those",
  "الكوكبة": "The Little Dipper",
  "صالحي": "Saalyheen",
  "الأمة": "The nation",
  "فأعتق": "So free",
  "رقبتين!": "Two necks!",
  "ومجالسة": "And companionship",
  "أقوام": "A group of people",
  "ينتقون": "They select",
  "أطايب": "Aṭayyib",
  "الكلام": "The discourse",
  "كما": "As well as",
  "يُنْتَقى": "is selected",
  "التمر!": "The date!",
  "وقال": "And he said,",
  "ثابت": "ثابت",
  "البناني:": "The Banani",
  "(أدركت": "(I understood",
  "رجالاً": "Men",
  "أحدهم": "One of them",
  "يصلي": "He prays",
  "فيعجز": "He is unable",
  "يأتي": "He comes",
  "فراشه": "Faraashah",
  "حبوًا!": "With passion!",
  "وضرب": "And He struck",
  "به": "By",
  "ساقه!": "Saqah!",
  "ويقول:": "He says:",
  "(أنت": "(You",
  "أولى": "Awwal",
  "بالضرب": "by striking",
  "دابتي!": "Dabati! [I am determined!]",
  "نظرت": "I looked",
  "السقف!": "The Ceiling!",
  "(ذهب": "He went",
  "نصف": "Half",
  "عملي!": "Work!",
  "ونفحات": "And breaths",
  "أريج": "Areej",
  "العارفين!": "The Knowing Ones!",
  "وتقلَّبُوا": "And they turned over",
  "رياض": "Riyad",
  "الصالحات!": "The righteous deeds!",
  "فحاسب": "So calculate",
  "أيُّها": "O",
  "العاقل:": "The Wise",
  "كيف": "How",
  "دعتك": "You were invited",
  "أمر": "Command",
  "فيه": "In it",
  "هواها؟": "What's its air?",
  "حينها": "Then",
  "العاصين": "the disobedient",
  "لها؟": "To her?",
  "أم": "Mother",
  "المسارعين": "The Swift Runners",
  "حاجتك": "Your need",
  "الإنسان": "The human",
  "عزم": "Resolve",
  "تُشْهِرُهُ": "She displays it",
  "سيفًا": "A sword.",
  "هوى": "He went down",
  "وشهواتها!": "And its desires!",
  "وتنتهي": "And it ends",
  "نواهيه": "he made him desist",
  "تنقاد": "Tunqad",
  "تهمل": "He neglects",
  "حسابها": "Her account",
  "حاسبتها": "I calculated it",
  "رجعت": "I returned",
  "قريب": "近",
  "فإنه": "Verily, it is",
  "فعليك": "So upon you",
  "بالصبر": "With patience.",
  "الأمور": "The matters",
  "كلها": "All of them",
  "ليكون": "To be",
  "الفائزين": "The winners",
  "بسعادة": "With happiness",
  "الدارين": "The two houses",
  "وجعلني": "And He made me",
  "وإيَّاك": "And you",
  "بنعيم": "with contentment",
  "جنَّاته": "His gardens",
  "والصَّلاة": "And prayer.",
  "والسَّلام": "And peace",
  "النَّبي": "The Prophet",
  "محمد": "Muhammad",
  "وآله": "And His family",
  "والأصحاب": "And the companions",
  "انظر": "Look",
  "رسالتنا:": "Our Message:",
  "ترياق": "Tiryaq",
  "الأحزان،": "Sorrows,",
  "وراحة": "And rest",
  "الأبدان": "The bodies",
  "الصبر": "Patience"
}