{
  "فوائد": "Beneficios",
  "ابن": "hijo",
  "الباغبان": "albáñez",
  "الكتاب:فوائد": "El libro: Beneficios",
  "(مطبوع": "(Impreso)",
  "ضمن": "Dentro de",
  "كتاب": "Libro",
  "جمهرة": "Gimberga",
  "الأجزاء": "las partes",
  "الحديثية)": "La historicidad)",
  "(المتوفى:": "(El fallecido:",
  "559هـ)": "Hijra year 559",
  "اعتناء": "Atención",
  "وتخريج:محمد": "Y la extracción de: Muhammad",
  "زياد": "Zaid",
  "تكلة": "Talea",
  "الرياض": "Riyad",
  "هـ": "H",
  "م": "م",
  "عدد": "número",
  "الأجزاء:1": "las partes:1",
  "[ترقيم": "Número",
  "الكتاب": "El libro",
  "موافق": "De acuerdo",
  "للمطبوع]": "Para la impresión]",
  "قَالَ:": "Dijo:",
  "كَانَ": "Era",
  "مِنْ": "De",
  "دُعَاءِ": "Oración",
  "النَّبِيِّ": "el Profeta",
  "صَلَّى": "صَلَّى",
  "اللَّهُ": "Dios",
  "عَلَيْهِ": "En él",
  "وَسَلَّم": "y envió saludos de paz",
  "اللَّهُمَّ": "Señor, amado de los ángeles y de las almas,\nseñor del reino celestial,\ny de la tierra y su contenido;\nsi te encomiendo a mi alma\nantes de morir,\npresérvala de las torturas del infierno,\nde las ansias del hambre,\ndel frío intenso,\nde los golpes dolorosos,\nde las cadenas que atan,\nde la opresión, el castigo y el mal;\ny de todo lo que te es contrario\ny de todo lo que no te agrada,\nOh Señor del universo.",
  "إِنِّي": "En realidad",
  "أَعُوذُ": "Me protejo",
  "بِكَ": "Con Él",
  "زَوَالِ": "zawāl",
  "نِعْمَتِكَ،": "Tu bendición,",
  "وَتَحَوُّلِ": "y el cambio",
  "عَافِيَتِكَ،": "Tu sanidad,",
  "وَفَجْأَةِ": "Y de repente,",
  "نِقْمَتِكَ،": "tu venganza,",
  "وَجَمِيعِ": "Y todos",
  "سَخَطِكَ": "tu cólera",
  "وَقَدْ": "Y ya",
  "وَقَعَ": "y cayó",
  "لَنَا": "Para nosotros",
  "مُوَافَقَةً": "Concordancia",
  "قَالَ": " dijo",
  "رَسُولُ": "madrugada",
  "اللَّهِ": "Al-láh",
  "دَخَلْتُ": "Entré",
  "الْجَنَّةَ،": "El Paraíso,",
  "فَرَأَيْتُ": "Entonces vi",
  "قَصْرًا": "forzadoamente",
  "وَدَارًا،": "y una casa,",
  "فَقُلْتُ:": "Entonces dije:",
  "لِمَنْ": "Para quién",
  "هَذِهِ؟": "¿Esta?",
  "قِيلَ:": "Se dijo:",
  "لِرَجُلٍ": "Para un hombre",
  "قُرَيْشٍ،": "Quraysh,",
  "فَرَجَوْتُ": "Entonces alivié",
  "أَنْ": "que",
  "أَكُونَ": "ser",
  "أَنَا": "Yo",
  "هُوَ،": "Él,",
  "وَقَالَ:": "Y dijo:",
  "يُغَارُ": "yegar",
  "عَلَيْكَ": "Sobre ti",
  "يَا": "¡Oh!",
  "رَسُولَ": "Mensajero",
  "اللَّهِ!": "¡Alláh!",
  "عَنِ": "Sobre",
  "ابْنِ": "Hijo",
  "عُيَيْنَةَ": "Oyeyna",
  "وَأَنْ": "Y también",
  "يَعُوهَا": "yayúha",
  "وَيَضَعُوهَا": "Y colocarán",
  "مَوَاضِعَهَا": "sus lugares",
  "لَأَقُومَنَّ": "¡Haré que me ponga de pie!",
  "بِهَا": "Con [ella/ello], o con ellos.",
  "فِي": "En",
  "أَوَّلِ": "Primer",
  "مَقَامٍ": "Posiciones",
  "أَقُومُهُ": "Lo levantaré.",
  "بِالْمَدِينَةِ": "En la ciudad",
  "وَلا": "y no",
  "فَإِنِّي": "Pues, en verdad yo",
  "لا": "No",
  "أُحِلُّ": "Se ha permitido",
  "لِأَحَدٍ": "para uno",
  "يَكْذِبَ": "mentiría",
  "عَلَيَّ": "Sobre mí",
  "قَال": " dijo",
  "تُطْرُونِي": "Me alaban o me halagan",
  "كَمَا": "Tal como",
  "أَطْرَتِ": "Atrat",
  "النَّصَارَى": "los cristianos",
  "ابْنَ": "Hijo",
  "مَرْيَمَ،": "María,",
  "فَإِنَّمَا": "Pues en verdad que",
  "عَبْدٌ،": "Esclavo",
  "فَقُولُوا:": "Entonces, decidle:",
  "عَبْدُهُ": "Abdú",
  "وَرَسُولُهُ": "Y su Mensajero",
  "ثُمَّ": "Luego,",
  "مَنْ": "¿Quién?",
  "خَبَّرَنَا،": "Nos informó,",
  "فَحَمِدَ": "Entonces alabó",
  "قَدْ": "Ciertamente",
  "دَفَّتْ": "daffat",
  "إِلَيْنَا": "Hacia nosotros",
  "دَافَّةٌ": "dáfiche",
  "مِنْكُمْ": "de ustedes",
  "فَقَالَ": "Entonces dijo:",
  "أَبُو": "Abu",
  "بَكْرٍ:": "báquer",
  "عَلَى": "sobre",
  "رِسْلِكَ": "Risalka",
  "وَبِيَدِ": "Y con la mano de",
  "أَبِي": "Abí",
  "عُبَيْدَةَ": "Ubaydah",
  "قَائِلٌ:": "diciendo:",
  "قَتَلْتُمْ": "Has matado",
  "سَعْدًا،": "Saúl",
  "قَتَلَ": "mató",
  "سَعْدًا": "Sa'ad",
  "وَلَيْسَ": "Y no",
  "فِيكُمْ": "En vosotros",
  "تُقْطَعُ": "Se corta",
  "إِلَيْهِ": "Hacia él",
  "الْأَعْنَاقُ": "El cuello",
  "مِثْلُ": "mismodopoder",
  "بَكْرٍ": "Bacrer",
  "رَضِيَ": "Ridí",
  "عَنْهُ": "Sobre él",
  "الزهري": "Al-Zuhri"
}