{
  "تنبيه": "Caution",
  "الحذاق": "The clever ones",
  "على": "Upon",
  "بطلان": "Invalidity",
  "ما": "What",
  "شاع": "شاع",
  "بين": "Between",
  "الأنام": "The creatures",
  "من": "From",
  "حديث": "Hadith",
  "النور": "The Light",
  "المنسوب": "The attributed",
  "لمصنف": "For the author",
  "عبد": "ʿAbd",
  "الرزاق": "The Provider",
  "محمد": "Muhammad",
  "أحمد": "Ahmed",
  "القادر": "al-Qadir",
  "الشنقيطي": "al-Shanqīṭī",
  "المدني": "Al-Madani",
  "الكتاب:تنبيه": "The book: Reminder",
  "المؤلف:محمد": "Author: Muhammad",
  "الناشر:الجامعة": "The publisher: The University",
  "الإسلامية": "The Islamic",
  "بالمدينة": "In Madinah",
  "المنورة": "The illuminated",
  "الطبعة:الثانية": "The second edition",
  "عدد": "Number",
  "الأجزاء:1": "The sections: 1",
  "[ترقيم": "[Numbering]",
  "الكتاب": "The book",
  "موافق": "Agreed",
  "للمطبوع]": "For printing",
  "تأليف:": "Authorship:",
  "الحمد": "The praise",
  "لله": "To God",
  "وحده": "And He is One",
  "والصَّلاة": "And prayer.",
  "والسلام": "And peace",
  "لا": "No.",
  "نبيَّ": " Prophet",
  "بعده": "After him",
  "وآله": "And His family",
  "وصحبه": "And his companions",
  "أما": "As for",
  "بعد": "After",
  "فقد": "But",
  "قرأت": "I read",
  "كتبه": "He wrote it.",
  "أخونا": "Our brother",
  "العلامة": "The scholar",
  "الشيخ": "The scholar",
  "بن": "bin",
  "الفقيه": "The jurist",
  "في": "In",
  "بيان": "Statement",
  "الأدلة": "The Evidence",
  "الحديث": "The Hadith",
  "إلى": "to",
  "مُصَنَّفِ": "Musa'abb",
  "الإمام": "The Imam",
  "همام": "Hammam",
  "الصنعاني": "Ash-Shanqiti",
  "رحمه": "May His mercy be upon him.",
  "الله": "Allah",
  "الدال": "The dhal",
  "أن": "Indeed, if a person were to perform an obligatory act within it, it would be as if he had performed seventy obligatory acts at other times.",
  "أول": "First",
  "المخلوقات": "The creatures",
  "هو": "He",
  "نور": "Nur",
  "نبينا": "Our Prophet",
  "صلى": "Pray",
  "عليه": "Upon him",
  "وسلم": "And do not exceed that,",
  "وأن": "And that",
  "كل": "All",
  "شيء": "Something",
  "خلق": "created",
  "ذلك": "That",
  "الخ": "The preceding text in the book was:",
  "فألقيته": "So I cast it",
  "قد": "Indeed,",
  "أجاد": "He did well",
  "فيما": "In what",
  "كتب": "He wrote,",
  "وأفاد": "And he provided",
  "وأبرز": "And the most prominent",
  "الدلائل": "The proofs",
  "والبراهين": "And the proofs",
  "النقلية": "al-naqliyyah",
  "والعقلية": "And intellectuality",
  "يدل": "It indicates",
  "هذا": "This",
  "وأنه": "And that",
  "جملة": "Sentence",
  "الأخبار": "The news",
  "الموضوعة": "set",
  "رسول": " Messenger",
  "وكل": "Every single one of them,",
  "تأمل": "Contemplate",
  "الشرعية": "Al-Shar'iyyah",
  "والسنة": "And the Sunnah",
  "علم": "Knowledge",
  "يقيناً": "Certainly",
  "الخبر": "The report",
  "الأباطيل": "The abatil",
  "التي": "The",
  "أساس": "Foundation",
  "لها": "To her",
  "الصحة": "Al-Sihah",
  "وقد": "And indeed",
  "أغنى": "Aghni",
  "نبيه": "Prophet",
  "عن": "On the authority of",
  "مثل": "Like",
  "بما": "With what",
  "أقام": "He stayed",
  "القاطعة": "The decisive one",
  "الساطعة": "The Brilliant One",
  "والمعجزات": "And the miracles",
  "الباهرة": "The Brilliant",
  "صحة": "Correctness",
  "نبوته": "His prophethood",
  "ورسالته": "And his message",
  "الصلاة": "The prayer",
  "كما": "As well as",
  "أغناه": "Aghnāhu",
  "المكذوب": "The Dissembler",
  "وأشباهه": "and similar things",
  "وهبه": "And He gave him",
  "الشمائل": "The Characteristics",
  "العظيمة": "The Great",
  "والصفات": "and the attributes",
  "الكريمة": "The Noble",
  "والأخلاق": "And ethics",
  "الرفيعة": "Al-Rafīʿah",
  "يشاركه": "He participates with him",
  "فيها": "In it",
  "أحد": "AHD",
  "ممن": "From those",
  "قبله": "Before him",
  "ولا": "And",
  "فهو": "Thus",
  "سيد": "My Lord",
  "ولد": "He was born",
  "آدم": "Adam",
  "وخاتم": "And the seal",
  "المرسلين": "The Messengers",
  "ورسول": "And the Messenger",
  "جميع": "All",
  "الثقلين": "The Two Weighty Things",
  "وصاحب": "And the companion",
  "الشفاعة": "The Intercession",
  "العظمى": "The greatest",
  "والمقام": "And the station",
  "المحمود": "The Praised",
  "يوم": "Day",
  "القيامة": "The Resurrection",
  "غير": "Not",
  "خصائصه": "His characteristics",
  "وشمائله": "And his characteristics",
  "وفضائله": "And his virtues",
  "الكثيرة": "The numerous",
  "وعلى": "And upon",
  "آله": "Allah",
  "وأصحابه": "And his companions",
  "ومن": "And among",
  "سلك": "Salk",
  "سبيله": "His way",
  "ونصر": "And we will grant victory",
  "دينه": "His religion",
  "وذبَّ": "He drove them away.",
  "شريعته": "His Shari'ah",
  "وحارب": "And fight",
  "خالفها": "Oppose her",
  "وأسأل": "And I ask",
  "يجزي": "He will repay",
  "أخانا": "Our brother",
  "عما": "Among",
  "المقام": "The Station",
  "جزى": "جزى",
  "به": "By",
  "المحسنين": "The righteous",
  "المدافعين": "The defenders",
  "نبيهم": "their prophet",
  "والعاملين": "And those who work",
  "نشرها": "He spread it",
  "والذَّب": "And the stinging",
  "عنها": "About her",
  "يجعلها": "He makes it",
  "وإياه": "And He",
  "وسائر": "And other",
  "إخواننا": "Our brothers",
  "دعاة": "Callers",
  "الهدى": "The Guidance",
  "وأنصار": "And the Helpers",
  "الحق": "the truth",
  "بقينا": "We remained",
  "إنه": "Indeed",
  "ولي": "And my",
  "والقادر": "And the Capable",
  "عبده": "His servant",
  "ورسوله": "and His Messenger",
  "سيدنا": "Our Lord",
  "وإمامنا": "And our leader",
  "أصحابه": "His companions",
  "اهتدى": "He guided",
  "بهداه": "With its brightness",
  "والحمد": "And all praise",
  "رب": "O Lord",
  "العالمين": "the worlds",
  "الرئيس": "The President",
  "العام": "The year",
  "إدارات": "Administrations",
  "البحوث": "Research",
  "العلمية": "The scientific",
  "والإفتاء": "And fatwa",
  "والدعوة": "And the call",
  "والإرشاد": "And guidance",
  "العزيز": "Al-'Aziz",
  "باز": "Bazz",
  "والصلاة": "And the prayer",
  "قال": "He said,",
  "تطروني": "Tatru",
  "أطرت": "I have turned away.",
  "النصارى": "The Christians",
  "عيسى": "Īsā",
  "مريم": "Maryam",
  "مبنى": "Structure",
  "عقيدتهم": "Their belief",
  "هذه": "This",
  "تدور": "It revolves.",
  "روى": "He narrated",
  "وجاء": "And it came",
  "المصنف": "The Compiler",
  "جابر": "Jabir",
  "رضي": "May Allāh be pleased with him/her/them.",
  "عنهما": "On them",
  "أنه": "Indeed",
  "سأل": "He asked",
  "خلقه": "His creation",
  "تعالى": "Exalted is",
  "والنصيحة": "And the advice",
  "لأهل": "For the people",
  "الإسلام": "Islam",
  "والديانة": "And religious obligations",
  "أكشف": "I will reveal",
  "بالنقد": "by cash",
  "والبحث": "And the research",
  "الحثيث": "The abundant",
  "مرتبة": "Rank",
  "اعتمد": "Depended",
  "هؤلاء": "These are",
  "عند": "At",
  "أهل": "People",
  "وأغزو": "And I will go on a military expedition",
  "وأصول": "and roots",
  "إن": "Indeed",
  "ثبت": "",
  "مصنف": "Mukhataba",
  "الطامَّات": "The overflowing",
  "العظام": "Bones",
  "ضمنه": "Within it",
  "أشار": "He pointed out,",
  "الحافظ": "al-Hafiz",
  "الحجر": "The Stone",
  "فإنه": "Verily, it is",
  "قال:": "He said:",
  "مصنفه": "Her compiler",
  "مشتمل": "Comprehensive",
  "عظائم": "The great misfortunes",
  "الأخبار1": "The News 1",
  "وهي": "And she is",
  "الإتصال": "The connection",
  "والضبط": "And [the] punctuation",
  "والعدالة": "And justice",
  "والمتابعة": "And monitoring",
  "المستور": "The imported",
  "وعدم": "and no",
  "الشذوذ": "The anomaly",
  "العلة": "The reason",
  "ثم": "Then",
  "وصل": "Arrived",
  "إليناً": "To us",
  "أخيراً": "Finally",
  "مطبوعاً": "Printed",
  "الهند": "India",
  "وليس": "And not",
  "فيه": "In it",
  "نسب": "Nasab",
  "إليه": "To him",
  "وأيضاً": "And also",
  "نص": "Text",
  "أئمة": "The Imams",
  "تقدَّمنا": "We advanced,",
  "وممن": "And among those",
  "عاصرنا": "We are contemporaries.",
  "وضعه": "He placed it.",
  "وضعفه": "And weakened it",
  "وجود": "Existence",
  "سند": "Narration",
  "له": "To him",
  "ثُمَّ": "Then",
  "اسْتَوَى": "He settled",
  "إِلَى": "To",
  "السَّمَاءِ": "The sky",
  "وَهِيَ": "And she is",
  "دُخَانٌ": "Smoke",
  "فَقَالَ": "Then he said,",
  "لَهَا": "To her",
  "وَلِلأَرْضِ": "And for the earth",
  "1الآيتان": "The two verses",
  "سورة": "Surah",
  "الرحمن": "The Most Gracious",
  "ولم": "And he did not",
  "يخصَّصوه": "It is specifically designated for them.",
  "يقيدوه": "He restrains him.",
  "بمقتضى": "By virtue of",
  "1الآيات": "The verses",
  "فصلت": "Al-Fatir",
  "2من": "2 of",
  "الآية": "The verse",
  "هود": "Hud",
  "قوله:": "His saying:",
  "أو": "Or",
  "يجب": "It is necessary",
  "الوقف": "The Waqf",
  "التساقط": "The falling off",
  "وفيه": "In it",
  "تفصيل": "Details",
  "حكاه": "He narrated it.",
  "الضابط": "The officer",
  "{وَجَعَلْنَا": "And We made,",
  "مِنَ": "منَ",
  "الْمَاءِ": "The water",
  "كُلَّ": "All",
  "شَيْءٍ": "Something",
  "حَيٍّ": "Living",
  "أَفَلا": "Is it not so that...",
  "يُؤْمِنُونَ}": "They believe",
  "فهذه": "This is",
  "آيات": "Verses",
  "خبريات": "Experiences",
  "يتجه": "He is heading towards...",
  "إليها": "To her",
  "النسخ": "نسخ",
  "دلت": "It is indicated",
  "معارضة": "Opposition",
  "دل": "Point",
  "المذكور": "The mentioned",
  "والحديث": "And the Hadith",
  "إذا": "If",
  "كان": "He was",
  "هكذا": "Thus",
  "يكون": "It will be",
  "موضوعاً": "Regarding",
  "بلا": "No",
  "شك": "No",
  "العلماء": "Scholars",
  "كحديث": "As in the Hadith",
  "مقدار": "The amount",
  "الدنيا": "The world",
  "وأنها": "And that she",
  "سبعة": "Seven",
  "آلاف": "Thousands",
  "سنة": "Year",
  "وأمثاله": "And similar to it",
  "مما": "From what",
  "خالف": "He differed",
  "صريح": "Explicit",
  "نصوص": "Texts",
  "القرآن\"": "The Quran",
  "انتهى": "It ends here.",
  "كلامه": "His speech",
  "وكتب": "And he wrote",
  "الذكر": "The Remembrance",
  "السموات": "The heavens",
  "والأرض\"": "And the earth",
  "وقال": "And he said,",
  "مجاهد": "Mujahid",
  "ووهب": "And He granted",
  "منبه": "Alarm",
  "وعمرة": "And 'Umrah",
  "وقتادة": "And Wadatha",
  "وغيرهم:": "and others",
  "عرشه": "His throne",
  "الماء": "The water",
  "قبل": "Before",
  "يخلق": "He creates",
  "وروى": "He narrated",
  "ابن": "Ibn",
  "جرير": "Jarir",
  "الطبري": "al-Tabari",
  "التفسير": "Interpretation",
  "حدثنا": "We were informed by",
  "بشار": "Bashar",
  "يحي": "Yahya",
  "سفيان": "Sufyan",
  "الأعمش": "al-A'mash",
  "أبي": "My father",
  "ظبيان": "Zubayyan",
  "عباس": "Abbas",
  "\"أول": "First",
  "القلم": "The Pen",
  "اكتب": "Write",
  "ماذا": "What",
  "أكتب؟": "Write?",
  "فجرى": "It flowed.",
  "اليوم": "Today",
  "قيام": "Rising",
  "الساعة": "The Hour",
  "النون": "The letter N",
  "ورفع": "And he raised",
  "بخار": "steam",
  "ففتقت": "Then they split apart",
  "منه": "From it",
  "السماء": "The Sky",
  "وبسطت": "And I have spread",
  "الأرض": "The Earth",
  "الخ\"": "The",
  "بتمامه": "Completely",
  "ورواه": "And they narrated it,",
  "والترمذي": "And at-Tirmidhi",
  "جامعه": "جامعه",
  "مرفوعاً": "Raised",
  "طريق": "Path",
  "الوليد": "The newborn",
  "عبادة": "Worship",
  "الصامت": "The Silent",
  "لي": "To me",
  "حين": "When",
  "حضرته": "He attended it.",
  "الوفاة": "Death",
  "سمعت": "I heard",
  "يقول:": "He says:",
  "\"إن": "Indeed,",
  "القلم:": "The Pen:",
  "فقال": "He said,",
  "له:": "For him:",
  "أكتب": "Write",
  "عمر": "Omar",
  "حبيب": "Beloved",
  "الثقات": "The Thiqat",
  "حميد": "Hamed",
  "قيس": "Qays",
  "الأعرج": "al-'Araj",
  "طاوس": "Tawus",
  "جاء": "He came",
  "البيهقي:": "Al-Bayhaqi:",
  "أراد": "He intended",
  "مصدر": "Source",
  "الجميع": "All",
  "أي": "Indeed",
  "وإبداعه": "And His creation",
  "واختراعه": "And his invention",
  "أولاً": "Firstly,",
  "وما": "And what",
  "شاء": "He desired",
  "أصل": "Origin",
  "مثال": "Example",
  "سبق": "preceded",
  "1الآية": "Ayah",
  "الجاثية": "Al-Jathiyyah",
  "كلام": "Speech",
  "البيهقي": "al-Bayhaqi",
  "إذ": "Indeed",
  "خرج": "He went out.",
  "الملائكة": "The angels",
  "والجن": "And the jinn",
  "ليسوا": "They are not",
  "مخلوقين": "created beings",
  "نطفة": "nutfah",
  "محتاجين": "Mandatory",
  "لماء": "For water",
  "الصحيح": "The correct",
  "فيه:": "In it:",
  "\"أنه": "Indeed,",
  "العرش": "The Throne",
  "تناهي": "Tunahy",
  "أنواعها": "Types of it",
  "ترجع": "She returns",
  "أصول": "Aqeedah",
  "الخمسة:": "The five:",
  "والنور": "And the light",
  "والظلمة": "and the darkness",
  "والرياح": "And the winds",
  "والتراب": "And the dust",
  "الأصول": "The Fundamentals",
  "الأنبياء": "The Prophets",
  "ويجوز": "And it is permissible.",
  "الإعراض": "Aversion",
  "والاعتماد": "And relying",
  "عليه!": "Upon him!",
  "سبحانك": "Glory be to You",
  "بهتان": "false accusation",
  "عظيم": "Great",
  "والأخرى": "and the other",
  "لقمان": " Luqman",
  "عامر": "Ummayr",
  "أمامة": "Amamah",
  "عنه": "From him",
  "كلا": "No",
  "منهما": "From them",
  "وسلم:": "and peace be upon him.",
  "\"ما": "What",
  "أمرك": "O my Lord",
  "يا": "O",
  "الله؟": "Allah?",
  "دعوة": "Call",
  "إبراهيم": "Ibrâhîm",
  "وبشرى": "And glad tidings",
  "فدعوى": "So the claim",
  "المعتمدين": "The dependents",
  "الصف": "The row",
  "2الآية": "The verse",
  "البقرة": "The Cow",
  "فتوقف": "He stopped",
  "وضع": "Position",
  "وإن": "And indeed",
  "فهذان": "And these two",
  "الحديثان": "The two hadiths",
  "شاهدان": "Two witnesses",
  "وهذا": "This",
  "أيضاً": "Also",
  "حديثاً": "Recently",
  "أصلا": "Essentially",
  "العقائد": "The Creed",
  "الدينية": "The religious",
  "إنهم": "Indeed, they are",
  "لم": "No",
  "يقنعوا": "They will be content",
  "بذلك": "With that",
  "حتى": "Until",
  "جعلوا": "They made",
  "معناه": "Its meaning",
  "الأحاديث": "The Hadiths",
  "يصلح": "He repairs",
  "شاهداً": "a witness",
  "يبلغ": "He reaches",
  "درجة": "Degree",
  "الاحتجاج": "The Protest",
  "الدين": "Religion",
  "وإليكم": "And to you",
  "الأول": "The first",
  "الحديثين": "The two Hadiths",
  "المذكورين": "Those mentioned",
  "الجوزي": "Al-Jawzi",
  "الموضاعات": "The topics",
  "الكبرى": "al-Kabīrah",
  "صفحة": "Page",
  "الجزء": "The Part",
  "الثاني": "The second",
  "منها:": "Of these:",
  "أنبأنا": "We have been informed",
  "الوهاب": "al-Wahhab",
  "المبارك": "The blessed",
  "وغيره": "And others like him.",
  "قالوا": "They said,",
  "المعطي": "The Bestower",
  "أبو": "Aby",
  "القاسم": "Al-Qāsim",
  "الحوفي": "al-Hawfi",
  "الدهقاني": "Al-Duhaqi",
  "حيان": "Hayan",
  "السكين": "The knife",
  "الصباح": "The morning",
  "علي": "ʿAlī",
  "الحسن": "The Good",
  "الكوفي": "The preceding text in the book was: ['...', '1.42%', '5', '...'].\n\nAl-Kufi.",
  "اليسع": "Al-Yāsīʿ",
  "العباس": "Al-Abbas",
  "الضرير": "The blind",
  "الخليل": "al-Khalīl",
  "مرة": "Once",
  "الجوزي:": "Al-Jawzi:",
  "موضوع": "Topic",
  "السبكين": "The two molars",
  "وإبراهيم": "And Ibrahim",
  "ويحي": "And he lives",
  "البصري": "al-Basri",
  "متروكون": "left behind",
  "ووافقه": "And he agreed with him",
  "حجر": "Stone",
  "والحافظ": "And the Preserver",
  "السيوطي": "As-Suyuti",
  "وأما": "As for",
  "الذهبي": "al-Dhahabi",
  "الميزان:": "The Balance",
  "عمرو": "Amr",
  "أوس": "A`us",
  "يجهلُ": "He is unaware.",
  "حاله": "His condition",
  "أتى": "He came.",
  "بخبر": "With news",
  "منكر": "denier",
  "أخرجه": "He transmitted it",
  "الحاكم": "The Ruler",
  "قسم": "Section",
  "الموضوع": "The Subject",
  "المستدرك": "The Mustadrak",
  "جندل": "Jundal",
  "واثق": "Confident",
  "الذهبي:": "Al-Dhahabi:",
  "أقوى": "The strongest",
  "الحجج": "Pilgrimage",
  "معتقدهم": "Their belief",
  "الذي": "The One",
  "وصفنا": "We have described",
  "المقدمة": "The introduction",
  "نظمه": "His moral characteristics:",
  "البوصيري": "al-Busiri",
  "تضمنته": "It contains it.",
  "ذكرنا": "We have mentioned",
  "لكم": "For you",
  "النصوص": "Texts",
  "كذبها": "She lied",
  "واختلافها": "And her difference",
  "بقوله": "With his saying",
  "الميمية:": "",
  "وكيف": "And how",
  "تدعو": "She calls",
  "ضرورة": "Necessity",
  "مَنْ": "Who",
  "لولاه": "Lolah",
  "تخرج": "She exits",
  "العدم": "The Nothingness",
  "وقوله:": "And His saying:",
  "ولن": "And never",
  "يضيق": "is narrow",
  "جاهك": "your support",
  "بي": "I am",
  "الكريم": "the Generous",
  "تجلى": "Tajalla",
  "باسم": "In the name of",
  "منتقم": "Avenger",
  "فإن": "If then,",
  "جودك": "Your generosity",
  "وضرتها": "And he made her ill",
  "علومك": "Your sciences",
  "اللوح": "The Tablet",
  "والقل": "And the heart",
  "غيره": "different from him/her/it",
  "نطقه": "His recitation",
  "وشكله:": "And its shape:",
  "خلقت": "I created",
  "شمس": "Sun",
  "قمر": "Moon",
  "نجوم": "Stars",
  "لوم": "لوم",
  "قلم": "Pen",
  "قريض": "Quraysh",
  "يميز": "differentiates",
  "صحيح": "True",
  "وضعيفه": "And weak",
  "يبالي": "He cares",
  "بتصحيحه": "With his correction",
  "تحريفه": "Distortion of it",
  "ولقد": "And indeed",
  "وقع": "It occurred",
  "بيني": "Between us",
  "وبين": "And between",
  "رجل": "Man",
  "يومًا": "One day",
  "سُكان": "Inhabitants",
  "شمال": "North",
  "موريتانيا": "Mauritania",
  "يقال": "It is said",
  "البار": "The Righteous One",
  "وهو": "And he",
  "شيعة": "Shi'a",
  "منهم": "from them",
  "وأتباع": "And followers",
  "يعتقدون": "They believe",
  "أعلم": "I inform you",
  "الخلق": "The creation",
  "وأولاهم": "And first among them",
  "بالله": "By Allah",
  "كلامٌ": "Speech",
  "ومناظرة": "And from among those who debate",
  "ألزمته": "He compelled him/her/it.",
  "الحجة": "The proof",
  "والدليل": "And the evidence",
  "يعتقده": "He believes him",
  "لولا": "But for",
  "تفضل": "Please",
  "تبارك": "Blessed is",
  "وتعالى": "Exalted is He",
  "الدواب": "al-dawāb",
  "والحشرات": "And insects",
  "بأي": "By which",
  "الأرزاق": "Provisions",
  "المنافع": "The benefit",
  "فاحتج": "So he argued",
  "عليَّ": "Upon me",
  "بقول": "With the saying",
  "البوصري": "al-Buṣrī",
  "المتقدم": "The advanced",
  "فقلت": "So I said",
  "قول": "Statement",
  "ليس": "Not",
  "بحجة": "as an excuse",
  "الشريعة": "The Sharia",
  "لي:": "To me:",
  "أفضل": "A better",
  "منك": "from you",
  "ويحك": "O woe to you",
  "متى": "When",
  "علمت": "I have learned",
  "منزلتي": "My station",
  "تعلم": "Learn",
  "لقي": "He met",
  "عنده": "With him",
  "فعلمت": "Thus I have come to know",
  "أتباعه": "Followers",
  "إخواني": "My brothers,",
  "وأين": "And where",
  "أمر": "Command",
  "محمدًا": "Muhammad",
  "يبلغنا": "He informs us",
  "{قُلْ": "Say,",
  "أَمْلِكُ": "Amalik",
  "لِنَفْسِي": "For myself",
  "نَفْعاً": "نَفْعاً",
  "وَلا": "But",
  "ضَرّاً": "ضَرّاً",
  "إِلاَّ": "But",
  "مَا": "What",
  "شَاءَ": "He willed",
  "اللَّهُ": "Allah",
  "وَلَوْ": "And if",
  "كُنْتُ": "I was",
  "أَعْلَمُ": "I am aware",
  "الْغَيْبَ": "The Unseen",
  "لاسْتَكْثَرْتُ": "I have not sought abundance",
  "الْخَيْرِ": "The good",
  "وَمَا": "and there is",
  "مَسَّنِيَ": "He touched me.",
  "السُّوءُ": "The evil",
  "إِنْ": "Indeed",
  "أَنَا": "I am",
  "نَذِيرٌ": "A Warner",
  "وَبَشِيرٌ": "And a bearer of good tidings,",
  "لِقَوْمٍ": "For a people",
  "تضلنا": "We have gone astray",
  "هديتنا": "Our guidance",
  "فنذكر": "So, we mention",
  "أيضًا": "Also",
  "الأعراف": "The Heights",
  "يعيذنا": "O our Lord! Protect us",
  "تفريط": "negligence",
  "المفرطين": "The excessive ones",
  "ولجاج": "Wulajaj",
  "المتعصبين": "The extremists",
  "لأوضاع": "To situations",
  "المبطلين": "The Invalidators",
  "آمين": "Amen.",
  "وصلى": "He sent blessings upon",
  "الأولين": "The first ones",
  "والآخرين": "And those others",
  "الطاهرين": "The Pure Ones",
  "الطيبين": "The righteous",
  "الفقير": "The poor",
  "مولاه": "My Lord",
  "منشأ": "Origin",
  "القرشي": "al-Qurashi",
  "نسبًا": "in proportion",
  "وطنًا": " homeland",
  "لثمان": "To eight",
  "ليالي": "The nights",
  "بقيت": "Remained",
  "شوال": "Shawwal",
  "عام": "Year",
  "1390هـ": "1390 AH",
  "وسميت": "And it was named",
  "الرسالة": "The Epistle"
}