{
  "منتقى": "Selected",
  "من": "From",
  "حديث": "Hadith",
  "الجصاص": "al-Jassas",
  "والحنائي": "al-Ḥanā'ī",
  "لأحمد": "For Ahmad",
  "بن": "bin",
  "عبد": "ʿAbd",
  "الدائم-": "The eternal",
  "مخطوط": "Manuscript",
  "(ن)": "(N)",
  "أحمد": "Ahmed",
  "الدائم": "The eternal",
  "الكتاب:منتقى": "The book: Selected",
  "زين": "Zayn",
  "الدين": "Religion",
  "الحنبلي": "Al-Hanbali",
  "(المتوفى:": "The deceased:",
  "668هـ)": "AH 668",
  "أعده": "He has returned it.",
  "للشاملة:أحمد": "To the comprehensive [book]: Ahmad",
  "الخضري": "al-Khadir",
  "[الكتاب": "[The Book",
  "مخطوط]": "manuscript",
  "الكتاب:": "The Book:",
  "المؤلف:": "The author:",
  "أبو": "Aby",
  "العباس": "Al-Abbas",
  "المقدسي": "al-Maqdisi",
  "المتوفى:": "Died:",
  "هـ": "H",
  "جزء": "Part",
  "فيه": "In it",
  "أبي": "My father",
  "يوسف": "Joseph",
  "يعقوب": "Jacob",
  "الدعَّا": "The caller",
  "ومن": "And among",
  "بكر": "Bukar",
  "الله": "Allah",
  "محمد": "Muhammad",
  "الحنائي": "Hanafi",
  "عن": "On the authority of",
  "شيوخه": "His teachers",
  "بسم": "In the name",
  "الرحمن": "The Most Gracious",
  "الرحيم": "The Most Merciful",
  "وصلى": "He sent blessings upon",
  "على": "Upon",
  "وآله": "And His family",
  "وسلم": "And do not exceed that,",
  "أخبرنا": "We were informed by",
  "الشيخ": "The scholar",
  "حمزة": "Hmza",
  "جميل": "Beautiful",
  "القرشي": "al-Qurashi",
  "أنبأ": "Anba'a",
  "هبة": "The gift",
  "الأنصاري": "Al-Ansari",
  "الاكفاني": "The Akfānī",
  "قراءةً": "Reading",
  "عليه": "Upon him",
  "في": "In",
  "السابع": "The seventh",
  "عشر": "Ten",
  "ذي": "Thawee",
  "القعدة": "Al-Qa'udah",
  "سنة": "Year",
  "عشرين": "twenty",
  "وخمسمائة": "And five hundred",
  "أخبركم": "I inform you",
  "القاسم": "Al-Qāsim",
  "الحسين": "al-Husayn",
  "إبراهيم": "Ibrâhîm",
  "الدمشقي": "The Dimashqi",
  "الحجة": "The proof",
  "ست": "Six",
  "وخمسين": "And fifty",
  "وأربعمائة": "And four hundred",
  "هلال": "Hilāl",
  "البغدادي": "al-Baghdadi",
  "بدمشق": "In Damascus",
  "قال:": "He said:",
  "ثنا": "We were informed by",
  "الدعّا:": "The caller",
  "حميد": "Hamed",
  "الخزاز": "The Khazzaz",
  "الطفاوي": "Al-Tifawī",
  "أيوب": "Ayyub",
  "زيد": "Zayd",
  "أسلم": "He embraced Islam.",
  "ابن": "Ibn",
  "عمر": "Omar",
  "((دخلت": "He entered",
  "رسول": " Messenger",
  "صلى": "Pray",
  "وعليه": "Upon that",
  "إزار": "Izar",
  "يتقعقع": "He/She/It quivers or shivers.",
  "حدثنا": "We were informed by",
  "هشيم": "Hisham",
  "الجهيم": "The Hell",
  "الزهري": "Az-Zuhri",
  "سلمة": "Salimah",
  "هريرة": "Hirira",
  "قال": "He said,",
  "وسلم:": "and peace be upon him.",
  "((امرؤ": "A certain person",
  "القيس": "al-Qays",
  "صاحب": "Owner",
  "لواء": "Lawa'",
  "الشعراء": "ash-Shu'araa",
  "النار": "The Fire",
  "الوليد": "The newborn",
  "إسحاق": "Ishaq",
  "الثوري": "Al-Thawri",
  "يزيد": "Ibn al-Jawziyyah",
  "زياد": "Ziyad",
  "مقسم": "Divided",
  "عباس": "Abbas",
  "((احتجم": "(he) cupped",
  "بين": "Between",
  "مكة": "Makkah",
  "والمدينة": "And the city",
  "وهو": "And he",
  "محرم": "Muharram",
  "صائم": "Fasting",
  "سيف": "Sword",
  "مالك": "Mālik",
  "مغول": "Mongol",
  "عطاء": "Giving",
  "((لعن": "Cursed",
  "سب": "Obligation",
  "أصحابي": "Companions",
  "المخرمي": "Al-Muhrami",
  "علي": "ʿAlī",
  "عاصم": "Utham",
  "ليث": "Liþ",
  "مجاهد": "Mujahid",
  "((أن": "Indeed",
  "جمع": "Compilation",
  "الصلاتين": "The two prayers",
  "الحضر": "The city dwellers",
  "والسفر": "And traveling",
  "روح": "Soul",
  "الفرج": "The relief",
  "إسماعيل": "Ismail",
  "أبان": "He explained",
  "حفص": "Hafs",
  "عمران": "Omar",
  "مسلم": "Muslim",
  "بياع": "Beiyaa' ",
  "الملاء": "The angels",
  "أنس": "Anas",
  "أجرى": "He conducted.",
  "خيبر": "Khaybar",
  "بالنصف": "By half",
  "فلما": "Then when",
  "بلغت": "بلغت",
  "بعث": "He sent",
  "رواحة": "Ruwāhah",
  "فشاطر": "Fashater",
  "القوم": "The people",
  "ثم": "Then",
  "خيرهم": "Their best",
  "أحد": "AHD",
  "الشطرين": "The two banks",
  "يحيى": "Yahya",
  "نصر": "victory",
  "حاجب": "Hajjaj",
  "شبرمة": "Shiborma",
  "((ما": "What",
  "أسكر": "I made someone drunk",
  "فخمر": "Fakhmar",
  "عبدان": "Abdān",
  "عثمان": "Uthman",
  "ميمون": "Maimun",
  "سمعت": "I heard",
  "أبا": "O my father",
  "أمية": "illiteracy",
  "يحدث": "He relates",
  "الحسن": "The Good",
  "حصين": "Hasan",
  "خطبنا": "We married off",
  "إلا": "Except",
  "أمرنا": "We have been commanded",
  "بالصدقة": "Through charity",
  "ق": "ق",
  "(أ)": "(A)",
  "ونهانا": "And He forbade us",
  "المثلة": "Al-Mithla",
  "رجاء": "Please",
  "الجارود": "al-Jarūd",
  "المنذر": "The Warner",
  "حجاج": "Hajj",
  "نصير": "Supporter",
  "مطيب": "Maitib",
  "عيسى": "Īsā",
  "سنان": "Sannan",
  "الضحاك": "al-Duha",
  "موسى": "Musa",
  "((كنا": "(We were)",
  "مع": "With",
  "النبي": "The Prophet",
  "غزوة": "The Battle of",
  "فرفع": "Then he raised",
  "بلال": "Bilal",
  "بالأذان": "With the call to prayer",
  "وكان": "And he was",
  "يؤذن": "Yūdhin",
  "بليل": "But by night",
  "فخرج": "He went out",
  "لحاجته": "Because of his need",
  "فدعا": "So he called",
  "بماء": "with water",
  "فتوضأ": "And he performed wudu.",
  "جبة": "Jabah",
  "فأخرج": "So bring out",
  "يده": "His hand",
  "تحتها": "beneath her",
  "ثلاثاً": "Three times",
  "ومسح": "And he wiped",
  "الجوربين": "al-juraybīn",
  "والنعلين": "And the two sandals",
  "الحكم": "The judgment",
  "((كان": "It was",
  "يصلي": "He prays",
  "والحمر": "And the red camels",
  "تعتري": "afflict",
  "يديه": "His hands",
  "سعيد": "Sa'eed",
  "الضرير": "The blind",
  "مكي": "Makki",
  "جريج": "Jareer",
  "عكرمة": "Uqaymirah",
  "مولى": "Master",
  "((نهى": "He forbade",
  "أن": "Indeed, if a person were to perform an obligatory act within it, it would be as if he had performed seventy obligatory acts at other times.",
  "يشرب": "He drinks.",
  "السقاء": "al-sāqā",
  "وعن": "And about",
  "المجثمة": "The compressed or The constrained",
  "والمجثمة:": "And the camel-burdened,",
  "الشاة": "The sheep",
  "ترمى": "The act of throwing or casting.",
  "بالنبل": "by means of excellence",
  "حتى": "Until",
  "تقتل": "You kill",
  "الجلالة": "The Sublime",
  "شاكر": "Grateful",
  "البختري": "Al-Bukhtari",
  "حسين": "Husayn",
  "الجعفي": "Al-Ja'fī",
  "عيينة": "Uyaina",
  "عمرو": "Amr",
  "دينار": "dinar",
  "((صلاة": "Prayer",
  "الجالس": "The seated one",
  "النصف": "The half",
  "صلاة": "Salah",
  "القائم": "The one who stands up",
  "داود": "David",
  "سفيان": "Sufyan",
  "نافع": "Nafi",
  "القزع": "Al-Qudhā' ",
  "عبيد": "Ubaid",
  "تمام": "Complete",
  "شهر": "month",
  "حوشب": "Huwashab",
  "((كل": "All",
  "كذب": "He lied",
  "مكتوب": "Written",
  "صاحبه": "his companion",
  "لا": "No.",
  "يحل": "Yahal",
  "له": "To him",
  "ثلاث": "Three",
  "يكذب": "He lies",
  "الرجل": "The man",
  "الرجلين": "The two men",
  "يصلح": "He repairs",
  "بينهما": "Between them",
  "ورجل": "And a man",
  "يعد": "He is counted among",
  "امرأته": "His wife",
  "الحرب": "The war",
  "والحرب": "And war",
  "خدعة": "deception",
  "الرِّبالي": "The Ribalite",
  "الوهاب": "al-Wahhab",
  "الثقفي": "Al-Thawfi",
  "يونس": "Yunus",
  "((أفطر": "I broke the fast",
  "الحاجم": "The Hājim",
  "والمحجوم": "And the one who has been tonsured",
  "الملك": "The King",
  "عامر": "Ummayr",
  "ويعقوب": "Jacob",
  "الحضرمي": "Al-Hadhrami",
  "قالا:": "They said:",
  "شعبة": "Subhah",
  "الأقمر": "The brighter moon",
  "جحيفة": "Jahhīfa",
  "((أما": "As for",
  "أنا": "I",
  "فلا": "Therefore",
  "آكل": "Eater",
  "متكئاً": "lying on a couch",
  "الأحوص": "Al-Ahwas",
  "حكيم": "Hakim",
  "خالد": "Khalid",
  "معدان": "Maidan",
  "عبادة": "Worship",
  "الصامت": "The Silent",
  "((صلى": "he prayed",
  "بنا": "With us",
  "شملة": "Sumlah",
  "قد": "Indeed,",
  "خالف": "He differed",
  "طرفيها": "its two sides",
  "وعقدها": "And he concluded it",
  "(ب)": "(b)",
  "عنقه": "His neck",
  "البلخي": "al-Balkhi",
  "هشام": "Hisham",
  "عروة": "ʿAro'ah",
  "أبيه": "My father",
  "جده": "His grandfather",
  "الزبير": "al-Zubayr",
  "((إن": "Surely",
  "الشعر": "Poetry",
  "حكمة": "Wisdom",
  "قراد": "A type of tick",
  "علية": "Upon him",
  "العزيز": "Al-'Aziz",
  "صهيب": "Suhayb",
  "يتزعفر": "It becomes dusty or covered with dust.",
  "سعدان": "Sa'adān",
  "معتمر": "Mu'tamir",
  "سليمان": "Solomon",
  "بشر": "Bashar",
  "الأعمش": "al-A'mash",
  "صالح": "Sāliḥ",
  "رضي": "May Allāh be pleased with him/her/them.",
  "عنه": "From him",
  "شريك": "Partner",
  "بنت": "Daughter",
  "شرحبيل": "Shurahabil",
  "الوارث": "The inheritor",
  "صخر": "صخر",
  "خصيف": "Khashif",
  "((لا": "",
  "بأس": "بأس",
  "ما": "What",
  "ابتسم": "He smiled.",
  "الصلاة": "The prayer",
  "عمر:": "Omar:",
  "وربما": "And perhaps",
  "تبسم": "He smiled.",
  "الواحد": "Al-Wāḥid",
  "النسائي": "An-Nasā'ī",
  "مصعب": "Musa'ab",
  "المقدام": "al-Muqaddam",
  "منصور": " Mansur",
  "وائل": "Wael",
  "مسعود": "Masood",
  "((في": "In",
  "القراءة": "Recitation",
  "خلف": "behind",
  "الإمام": "The Imam",
  "أنصت": "Listen attentively.",
  "للقرآن": "To the Quran",
  "فإن": "If then,",
  "شغلاً": "work",
  "وسيكفيك": "And He will suffice you",
  "ذلك": "That",
  "الشيباني": "Ash-Shaybānī",
  "الشعبي": "Ash-Sha'abi",
  "الهاشمي": "al-Hashimi",
  "قبر": "grave",
  "((إذا": "If",
  "استيقظ": "He awoke.",
  "أحدكم": "One of you",
  "منامه": "منامه",
  "يغمس": "yugmus",
  "الإناء": "The vessel",
  "يغسلها": "He washes it.",
  "الحارث": "Al-Harith",
  "المغيرة": "Al-Mughīrah",
  "يمنعن": "they prevent",
  "سحوره": "Suhoor",
  "أذان": "Athan",
  "فإنه": "Verily, it is",
  "ينادي": "He calls out",
  "أو": "Or",
  "ليرجع": "To return",
  "قائمكم": "Your leader",
  "ولينبه": "And let them be reminded",
  "نائمكم": "Sleepers",
  "وقال:": "And he said:",
  "وليس": "And not",
  "الفجر": "The Dawn",
  "الصبح": "The dawn",
  "هكذا": "Thus",
  "يكون": "It will be",
  "الفضل": "al-Fuḍl",
  "[الرخامي]": "The marble",
  "الفريابي": "al-Farabi",
  "جابر": "Jabir",
  "((رأيت": "",
  "ثوب": "garment",
  "واحد": "One",
  "متوشحاً": "with a shroud",
  "به": "By",
  "والظاهر": "And what is outward/apparent",
  "الناسخ": "The abrogating",
  "أراد": "He intended",
  "بها": "In her",
  "تعريف": "Definition",
  "اسم": "Name",
  "\"الفضل\"": "The Favour",
  "لهذا": "For this reason",
  "أضفتها": "I added it.",
  "سياق": "Context",
  "النص": "",
  "الأرقم": "Al-'Arqam",
  "((أنه": "(That he",
  "خرج": "He went out.",
  "حج": "Hajj",
  "عمرة": "Umrah",
  "فكان": "Then it became",
  "يؤم": "He leads prayers or performs Hajj",
  "أصحابه": "His companions",
  "حضرت": "I was present.",
  "ليؤمكم": "to lead you",
  "بعضكم": "Some of you",
  "فإني": "Indeed,",
  "يقول:": "He says:",
  "إذا": "If",
  "وأراد": "And he intended",
  "الحاجة": "The need",
  "فليبدأ": "Let him begin",
  "بالحاجة": "By need",
  "حسان": "Hasan",
  "هارون": "Harun",
  "التيمي": "al-Tamimi",
  "تواجه": "You face",
  "المسلمين": "The believers",
  "بسيفيهما": "With their swords",
  "فالقاتل": "The killer",
  "والمقتول": "And the one who is killed",
  "قيل:": "It is said:",
  "يا": "O",
  "فما": "So what",
  "بال": "With",
  "المقتول؟": "The one who was killed?",
  "إنه": "Indeed",
  "قتل": "He killed",
  "قيل": "It is said",
  "له:": "For him:",
  "ذكره": "He mentioned him/her/it.",
  "جعفر": "Ja'far",
  "وابن": "And Ibn",
  "ليلى": "Layla",
  "مكحول": "Makhaal",
  "((أنهم": "(That they",
  "قالوا:": "They said:",
  "أين": "Where",
  "نجعل": "We make",
  "الإزار؟": "The izar?",
  "إلى": "to",
  "نصف": "Half",
  "الساقين": "The shins",
  "فأسفل": "Then below",
  "ذلك؟": "That?",
  "الكعبين": "The two al-Ka'bs",
  "أسفل": "Below",
  "ففي": "For in",
  "النار)": "Fire",
  "الركن": "The Pillar",
  "الحائض": "The menstruating woman",
  "(لك": "For you",
  "السرة": "The Sura",
  "فوق": "Above",
  "الركبتين": "The two knees",
  "كلمة": "word",
  "غير": "Not",
  "مفهومة": "understood",
  "وأثبت": "And he established",
  "الراجح": "The preponderant",
  "عندي": "I have",
  "بالأصل": "Originally",
  "وسالت": "And I asked",
  "دُموعه))": "His tears",
  "سهيل": "Suhayl",
  "تبدءوهم": "You start them",
  "بالسلام": "With peace",
  "وإذا": "And if",
  "لقيتموهم": "you have met them",
  "طريق": "Path",
  "فاضطروهم": "They were forced",
  "أضيقها": "Aḍīquhā",
  "يعني": "It means",
  "أهل": "People",
  "العهد": "The covenant",
  "المنكدر": "The dispraiser",
  "كثيره": "Much",
  "فقليله": "For his little",
  "حرام": "Forbidden",
  "وكفارته": "And its expiation",
  "كفارة": "Expiation",
  "يمين": "Right",
  "الحجاج": "The Pilgrims",
  "البراء": "Al-Burā' or Al-Burā'a",
  "حدثهم": "He told them",
  "كان": "He was",
  "والله": "And God",
  "لولا": "But for",
  "اهتدينا": "We have found guidance.",
  "ولا": "And",
  "تصدقنا": "We testify.",
  "صلينا": "We prayed.",
  "فأنزلن": "Then We sent down",
  "سكينةً": "Sakinah",
  "علينا": "Upon us",
  "وثبت": "And it has been established",
  "الأقدام": "The feet",
  "إن": "Indeed",
  "لاقينا": "We met",
  "الأولى": "The first",
  "بغوا": "They rebelled",
  "علينا))": "Upon us",
  "الطوسي": "al-Tūsī",
  "الفضيل": "al-Fadil",
  "عمار": "I'm sorry, I don't know the answer to that.",
  "الدهني": "The fatty",
  "((رفع": "He raised",
  "رجل": "Man",
  "مات": "He died.",
  "دين": "Religion",
  "وله": "And for him,",
  "غلام": "young male servant",
  "مدبر": "Mediator",
  "فباعه": "He sold him",
  "علوية": "Alawite",
  "علقمة": "Al-ʿIqma",
  "عائشة": "A'ishah",
  "يباشر": "He will start",
  "جوان": "Ghawwān",
  "رزين": "Razin",
  "المثنى": "Dual",
  "قتادة": "Qatada",
  "الوصال": "Al-Wusool",
  "فإنك": "Indeed, you",
  "تواصل": "Continue",
  "ربي": "Rabbī",
  "يطعمني": "He feeds me",
  "ويسقيني": "And He will give me to drink",
  "قالت:": "She said:",
  "((طيبت": "Good",
  "يوم": "Day",
  "النحر": "The offering of sacrifice",
  "بعدما": "After",
  "رمي": "Throwing",
  "الجمرة": "The black stone",
  "آخر": "Last",
  "انتخبت": "Elected",
  "الجزء": "The Part",
  "الأول": "The first",
  "شبابة": "شَبَابَة",
  "المتوكل": "Al-Mutawakkil",
  "الحجامة": "Hijamah",
  "للصائم": "for the fasting person",
  "((إنما": "Indeed",
  "كرهت": "I disliked",
  "أجل": "Indeed",
  "الضعف": "weakness",
  "جرير": "Jarir",
  "الموالي": "The freed slaves",
  "عقيل": "Uqayl",
  "((لولا": "But if it were not for...",
  "أشق": "Ashiq",
  "أمتي": "My nation",
  "لأمرتهم": "I have commanded them",
  "بالسواك": "Using a siwak",
  "كل": "All",
  "غالب": "Most",
  "عباد": "O servants",
  "أخبرني": "He informed me",
  "سمع": "He heard",
  "الدباء": "The dabbā'ah",
  "والنقير": "And al-Naqir",
  "والمزفت": "And the asphalt",
  "هذا": "This",
  "الحديث": "The Hadith",
  "كتبه": "He wrote it.",
  "مكرراً": "repeatedly",
  "وقد": "And indeed",
  "شطب": "Erase",
  "فقمت": "I stood up",
  "بحذف": "With deletion",
  "المكرر": "The repeated",
  "حَتَّى": "Until",
  "غَابَتِ": "Ghabat",
  "الشَّمْسُ": "The Sun",
  "النضر": "al-Nadr",
  "بشير": "Bashir",
  "نهيك": "I'm sorry, I don't know the answer to that.",
  "نهى": "he forbade",
  "خاتم": "Seal",
  "الذهب)": "Gold",
  "جريج:": "Jareer",
  "الخوار": "al-Khawar",
  "أنه": "Indeed",
  "(بينا": "(Between",
  "يأكل": "He eats.",
  "عرقاً": "عرقاً",
  "فأتاه": "He came to him",
  "المؤذن": "The caller",
  "فقام": "He stood up",
  "ولم": "And he did not",
  "يمس": "He touches",
  "ماءاً": "water",
  "قيس": "Qays",
  "احتجم": "Cupped",
  "وجع": "Soreness",
  "عرض": "Exhibition",
  "تزوج": "He married",
  "ميمونة": "Maimunah",
  "صرد": "To arrange",
  "حماد": "Hammad",
  "عجل": "Hasten",
  "السير": "The biographies",
  "الظهر": "Al-Zuhur",
  "والعصر": "And by the time",
  "وبين": "And between",
  "المغرب": "The Maghreb",
  "والعشاء": "and the evening meal",
  "الفزاري": "al-Fazārī",
  "إسرائيل": "Israel",
  "لجعلت": "To make",
  "عليهم": "Upon them",
  "السواك": "Toothbrush",
  "عند": "At",
  "الربالي": "al-Rabali",
  "حدثني": "He narrated to me",
  "بعد": "After",
  "رجم": "Rajm",
  "الأسلمي": "Al-Aisami",
  "((اجتنبوا": "Avoid",
  "هذه": "This",
  "القاذورة": "The garbage",
  "التي": "The",
  "عنها": "About her",
  "فمن": "And whoever",
  "ألم": "Ow!",
  "فليستتر": "Let him cover.",
  "بستر": "With a covering",
  "عز": "Vexation",
  "وجل": "And He is Glorious",
  "الزعفراني": "al-Zuhafrani",
  "محمود": "Mahmoud",
  "لبيد": "Labid",
  "رافع": "Rafaa",
  "خديج": "Khadija",
  "((أسفروا": "Break your fast",
  "بالفجر": "At dawn",
  "أعظم": "The greatest",
  "للأجر": "For the reward",
  "كثير": "Much",
  "الأوزاعي": "al-Awza'i",
  "وأبو": "And Abu",
  "وعمر": "And 'Umar",
  "يفتتحون": "They open",
  "بالحمد": "With gratitude",
  "لله": "To God",
  "رب": "O Lord",
  "العالمين": "the worlds",
  "المروزي": "al-Marwazi",
  "الأشعري": "al-Ash'ari",
  "النهشلي": "al-Nahshali",
  "المقبري": "al-Maqburi",
  "يبغض": "He hates",
  "جعظري": "Jawharī",
  "جواظ": "Jawaz",
  "سخاب": "Sakhāb",
  "الأسواق": "The markets",
  "جيفة": "corruption",
  "بالليل": "In the night",
  "حمار": "Donkey",
  "النهار": "The Day",
  "عالم": "Scholar",
  "بالدنيا": "in this world",
  "جاهل": "ignorant",
  "بالآخرة": "In the Hereafter",
  "بيان": "Statement",
  "بالهاجرة": "By migration",
  "فقال:": "He said:",
  "((أبردوا": "Abruddu",
  "بالظهر": "At noon",
  "شدة": "intensity",
  "الحر": "The Hot One",
  "فيح": "فيح",
  "جهنم": "Jannah",
  "خارجة": "Outgoing",
  "حبيب": "Beloved",
  "أزدك": "Azdak",
  "رباح": "Rabah",
  "ماهك": "What is it?",
  "((ثلاث": "Three",
  "جدهن": "Their grandmother",
  "جد": "grandfather",
  "وهزلهن": "and their jesting",
  "الطلاق": "Divorce",
  "والعتاق": "The freed ones",
  "والرجعة": "And the Return",
  "ثُمَّ": "Then",
  "أَمَرَ": "He commanded",
  "بِكُلِّ": "With every",
  "كِسْرَةٍ": "Kisrah",
  "فَغُرِسَتْ": "Then it was planted.",
  "والصحيح": "And the correct",
  "\"أبو": "Abu",
  "الأشعري\"": "al-Ash'ari",
  "مكتوبة": "Written",
  "بالهامش": "In the margin",
  "كأن": "It is as if",
  "نسي": "He forgot",
  "يكتبها": "He writes them",
  "السطر": "The line",
  "فاستدركها": "So he rushed to catch up with her",
  "ق6": "Q6",
  "أَوْ": "Or",
  "لَمْ": "There has been none",
  "تَيْبَسَا": "Taybasa",
  "القزاز": "The clothier",
  "أشعث": "ash-`uth",
  "الربيع": "The spring",
  "طاووس": "Tawūs",
  "مذعور": "Mudzhar",
  "شعيب": "Shu'ayb",
  "طلاق": "Divorce",
  "ملاك": "Malaik",
  "عتاق": " Freed slaves",
  "املاك": "Properties",
  "الليث": "Al-Lith",
  "عجلان": "Ajaalan",
  "يسار": "Yasar",
  "الخدري": "al-Khadri",
  "يدري": "He knows",
  "كم": "How many",
  "أواحدة": "One",
  "اثنتين": "two",
  "أربعاً": "Fourthly",
  "فليبن": "Let them build",
  "استيقن": "Believe firmly",
  "يسجد": "He prostrates.",
  "سجدتين": "Two prostrations.",
  "قبل": "Before",
  "السلام": "Peace",
  "العوام": "The common people",
  "سهل": "Simple",
  "حنيف": "Hunayf",
  "((يأتي": "It comes",
  "قوم": "People",
  "المشرق": "The East",
  "محلقة": "Muhallakah",
  "رؤوسهم": "Their heads",
  "فسئل": "He was asked",
  "المدينة": "Al-Madinah",
  "آمناً": "Believing",
  "مرتين": "Twice",
  "حنبل": "Hanbal",
  "محارب": "Muharib",
  "يشير": "He points out,",
  "بإصبعه": "With his finger",
  "\"أو": "Or",
  "ثلاثاً\"": "Three times.",
  "ومشطب": "And polished",
  "عليها": "Upon it",
  "فلعل": "For perhaps",
  "أخطأ": "A'it",
  "أدرك": "He caught up with",
  "خطأه": "His mistake",
  "منيع": "مُنَعٍ",
  "((لبيك": "(I am) present at your command.",
  "بحجة": "as an excuse",
  "وعمرة": "And 'Umrah",
  "طالب": "Student",
  "الزبيري": "al-Zubayri",
  "مرثد": "Mardath",
  "بريدة": "Burai'dah",
  "يعلمهم": "He teaches them",
  "دخلوا": "They entered.",
  "المقابر": "The graveyards",
  "قائلهم": "One of them said",
  "عليكم": "Upon you",
  "الديار": "The cities",
  "المؤمنين": "The believers",
  "والمسلمين": "And the believers",
  "وإنا": "And we",
  "بكم": "By how much?",
  "لاحقون": "Lahiqun",
  "نسأل": "We ask",
  "لنا": "For us",
  "ولكم": "And for you",
  "العافية": "al-`afiyah",
  "للانتخاب": "For election",
  "الثاني": "The second",
  "وهذا": "This",
  "الحنائي:": "Al-Hanawī:",
  "طاهر": "طاهر",
  "بركات": "Blessings",
  "الخشوعي": "Al-Khasha'iy",
  "أنأ": "I am",
  "رمثه": "Ramthah",
  "رفاعة": "Rafaa",
  "يثربي": "Yathrib",
  "إِلَيْهِ": "To Him",
  "الأوزاعي:": "Al-Awzai'i:",
  "شداد": "Shaddad",
  "المسائل": "The Issues",
  "وضعافها": "And those who are weak",
  "سالم": "Salam",
  "يفتتح": "he opens",
  "يرفع": "He raises",
  "يجاوز": "exceeds",
  "منكبيه": "his shoulders",
  "يركع": "He bends",
  "وبعد": "And after that,",
  "الركوع": "Ruk'ah",
  "السجدتين": "The two prostrations",
  "\"بسر": "With ease or readily.",
  "سعيد\"": "Sa'id",
  "حرب": "war",
  "البجلي": "Al-Bajali",
  "((كنت": "I was",
  "فأتى": "He came",
  "الخلاء": "The bathroom",
  "فقضى": "He decreed,",
  "هات": "Hāt",
  "طهور": "Purity",
  "فأتيته": "Then I came to him",
  "فاستنجأ": "Fustanja",
  "بالماء": "With water",
  "وقال": "And he said,",
  "بيده": "with his hand",
  "فدلك": "And He has given you",
  "الأرض": "The Earth",
  "توضأ": "He performed wudu (ablution).",
  "غسل": "Wash",
  "وجهه": "Turn his face",
  "ويديه": "And his hands",
  "برأسه": "With his head",
  "وعلى": "And upon",
  "خفيه": "خفيه",
  "قلت": "",
  "نبي": "Prophet",
  "رجليك": "Your feet",
  "أدخلتهما": "I entered them",
  "طاهرتان": "Pure",
  "القلانسي": "al-Qalanisi",
  "آدم": "Adam",
  "خنيس": "Khunays",
  "الشامي": "Ashamī",
  "غنم": "Sheep",
  "معاذ": "Ma'ud",
  "جبل": "Jabal",
  "فمسح": "Famash",
  "بطرف": "with one side",
  "ثوبه)": "his garment",
  "(من": "(from",
  "أتى": "He came.",
  "النساء": "The Women",
  "والرجال": "And the men",
  "أدبارهن": "their backs",
  "فقد": "But",
  "كفر": "Disbelief",
  "((سئل": "He was asked,",
  "طلق": "He divorced",
  "فتزوجها": "So he married her",
  "فطلقها": "So he expelled her",
  "يواقعها": "He has relations with her",
  "فهل": "Is it then",
  "تحل": "It is permissible.",
  "للأول؟": "For the first one?",
  "للأول": "To the first",
  "يذوق": "he will taste",
  "الآخر": "the last",
  "عسيلتها": "honey",
  "الكرابيسي": "al-Karabīsī",
  "دخل": "entered",
  "فتح": "Fath",
  "عمامة": "headcloth",
  "سوداء": "Black",
  "يوجد": "There exists",
  "خطأ": "Error",
  "فلم": "So why",
  "أثبته": "He confirmed it",
  "النيسابوري": "An-Naysaburi",
  "مصفى": "purified",
  "بقية": "The rest",
  "المعتمر": "The one who performs the lesser pilgrimage (umrah)",
  "عبيدة": "Abiyyad",
  "أكلتم": "Have you eaten?",
  "الفجل": "The fennel",
  "فأردتم": "So you intended",
  "ريح": "wind",
  "فاذكروني": "So remember Me",
  "أول": "First",
  "قضمة": "A small or sharp bite",
  "الرازي": "al-Razi",
  "المؤمن": "Al-Mu'min",
  "((ويل": "Woe!",
  "للعراقيب": "For the 'Iraqiyyib",
  "مسهر": "Mash'oor",
  "المازني": "al-Ma'zuni",
  "يقطع": "He cuts off",
  "الوادي": "The valley",
  "سعياً": "Seeking",
  "الطائي-": "al-Tayyā’i",
  "عمارة": "Construction",
  "((جمع": "Gather",
  "بجمع": "With collection",
  "الحراني": "al-Harani",
  "عوف": "Ouf",
  "الضمري": "al-Dumari",
  "يمسح": "he wipes",
  "الخفين": "The two sandal",
  "العمامة": "The turban",
  "كتب": "He wrote,",
  "إلي": "To",
  "وأبي": "And Abu",
  "عنهما": "On them",
  "فكانوا": "They were",
  "يستفتحون": "They will open it",
  "يذكرون": "They mention",
  "قراءته": "His reading",
  "آخرها": "Lastly",
  "معاوية": "Mu'awiyah",
  "زائدة": "Zayda",
  "يساف": "Yusuf",
  "الجعد": "The curly-haired",
  "وابصة": "And [as for] the blind",
  "معبد": "Temple",
  "رأى": "He saw",
  "رجلاً": "A man",
  "لم": "No",
  "بالصفوف": "In ranks",
  "فأمره": "He commanded him",
  "يعيد": "He will return.",
  "الأيلي": "al-A'ili",
  "بثام": "Bitham",
  "وأمه": "And his mother",
  "ابنة": "daughter",
  "خالد:": "Khalid:",
  "جاء": "He came",
  "أذنه": "His permission",
  "قرطاً": "a pair of earrings",
  "وفي": "And regarding",
  "رأسه": "his head",
  "ذؤابة": "ذؤابة",
  "فأخذه": "So he took him",
  "شهاب": "Shahab",
  "فأدخله": "So bring him in",
  "أهله": "His family",
  "ألا": "Is it not that...",
  "تعجبون": "You are amazed",
  "الغلام": "The youth",
  "يطلب": "He seeks",
  "العلم)": "Knowledge.",
  "أخر": "The last",
  "استخرجته": "He extracted it",
  "فوائد": "Benefits",
  "أعلم": "I inform you"
}